{"data": {"context": {"status": "incomplete", "sessionId": "Cl0IARJZCk4KJDQxNWVlMzdlLWY2ZDMtNGI4OC1iMjM1LTZlZTRkMmUxZWU5ORACGiQwNTE4YTBhMS1lY2Y3LTQ3ODctODIyYi03Yzc4MDA5MjM1NmMQvsjxz9YyGAESKHVzc180MTgwZTNjYi1lMDg4LTQyODItODJhYS1jYThlNjZkMTljZGYiAlVT", "totalResults": 10}, "itineraries": [{"id": "10002-2503062020--32348-1-12712-2503070815", "price": {"raw": 73673.0, "formatted": "\u20b9\u00a073,673", "pricingOptionId": "aefLkdkEKcKc"}, "legs": [{"id": "10002-2503062020--32348-1-12712-2503070815", "origin": {"id": "BLR", "entityId": "95673351", "name": "Bengaluru", "displayCode": "BLR", "city": "Bengaluru", "country": "India", "isHighlighted": false}, "destination": {"id": "JFK", "entityId": "95565058", "name": "New York John F. Kennedy", "displayCode": "JFK", "city": "New York", "country": "United States", "isHighlighted": false}, "durationInMinutes": 1345, "stopCount": 1, "isSmallestStops": false, "departure": "2025-03-06T20:20:00", "arrival": "2025-03-07T08:15:00", "timeDeltaInDays": 1, "carriers": {"marketing": [{"id": -32348, "alternateId": "EK", "logoUrl": "https://logos.skyscnr.com/images/airlines/favicon/EK.png", "name": "Emirates"}], "operationType": "fully_operated"}, "segments": [{"id": "10002-11182-2503062020-2503062300--32348", "origin": {"flightPlaceId": "BLR", "displayCode": "BLR", "parent": {"flightPlaceId": "IBLR", "displayCode": "BLR", "name": "Bengaluru", "type": "City"}, "name": "Bengaluru", "type": "Airport", "country": "India"}, "destination": {"flightPlaceId": "DXB", "displayCode": "DXB", "parent": {"flightPlaceId": "DXBA", "displayCode": "DXB", "name": "Dubai", "type": "City"}, "name": "Dubai", "type": "Airport", "country": "United Arab Emirates"}, "departure": "2025-03-06T20:20:00", "arrival": "2025-03-06T23:00:00", "durationInMinutes": 250, "flightNumber": "567", "marketingCarrier": {"id": -32348, "name": "Emirates", "alternateId": "EK", "allianceId": 0, "displayCode": ""}, "operatingCarrier": {"id": -32348, "name": "Emirates", "alternateId": "EK", "allianceId": 0, "displayCode": ""}}, {"id": "11182-12712-2503070235-2503070815--32348", "origin": {"flightPlaceId": "DXB", "displayCode": "DXB", "parent": {"flightPlaceId": "DXBA", "displayCode": "DXB", "name": "Dubai", "type": "City"}, "name": "Dubai", "type": "Airport", "country": "United Arab Emirates"}, "destination": {"flightPlaceId": "JFK", "displayCode": "JFK", "parent": {"flightPlaceId": "NYCA", "displayCode": "NYC", "name": "New York", "type": "City"}, "name": "New York John F. Kennedy", "type": "Airport", "country": "United States"}, "departure": "2025-03-07T02:35:00", "arrival": "2025-03-07T08:15:00", "durationInMinutes": 880, "flightNumber": "203", "marketingCarrier": {"id": -32348, "name": "Emirates", "alternateId": "EK", "allianceId": 0, "displayCode": ""}, "operatingCarrier": {"id": -32348, "name": "Emirates", "alternateId": "EK", "allianceId": 0, "displayCode": ""}}]}], "isSelfTransfer": false, "isProtectedSelfTransfer": false, "farePolicy": {"isChangeAllowed": false, "isPartiallyChangeable": false, "isCancellationAllowed": false, "isPartiallyRefundable": false}, "fareAttributes": {}, "isMashUp": false, "hasFlexibleOptions": false, "score": 0.999}, {"id": "10002-2503062200--32672-1-12712-2503070655", "price": {"raw": 74126.81, "formatted": "\u20b9\u00a074,127", "pricingOptionId": "MOvuFyoWvfDE"}, "legs": [{"id": "10002-2503062200--32672-1-12712-2503070655", "origin": {"id": "BLR", "entityId": "95673351", "name": "Bengaluru", "displayCode": "BLR", "city": "Bengaluru", "country": "India", "isHighlighted": false}, "destination": {"id": "JFK", "entityId": "95565058", "name": "New York John F. Kennedy", "displayCode": "JFK", "city": "New York", "country": "United States", "isHighlighted": false}, "durationInMinutes": 1165, "stopCount": 1, "isSmallestStops": false, "departure": "2025-03-06T22:00:00", "arrival": "2025-03-07T06:55:00", "timeDeltaInDays": 1, "carriers": {"marketing": [{"id": -32672, "alternateId": "AI", "logoUrl": "https://logos.skyscnr.com/images/airlines/favicon/AI.png", "name": "Air India"}], "operationType": "fully_operated"}, "segments": [{"id": "10002-10957-2503062200-2503070040--32672", "origin": {"flightPlaceId": "BLR", "displayCode": "BLR", "parent": {"flightPlaceId": "IBLR", "displayCode": "BLR", "name": "Bengaluru", "type": "City"}, "name": "Bengaluru", "type": "Airport", "country": "India"}, "destination": {"flightPlaceId": "DEL", "displayCode": "DEL", "parent": {"flightPlaceId": "IDEL", "displayCode": "DEL", "name": "New Delhi", "type": "City"}, "name": "Indira Gandhi International ", "type": "Airport", "country": "India"}, "departure": "2025-03-06T22:00:00", "arrival": "2025-03-07T00:40:00", "durationInMinutes": 160, "flightNumber": "2814", "marketingCarrier": {"id": -32672, "name": "Air India", "alternateId": "AI", "allianceId": 0, "displayCode": ""}, "operatingCarrier": {"id": -32672, "name": "Air India", "alternateId": "AI", "allianceId": 0, "displayCode": ""}}, {"id": "10957-12712-2503070230-2503070655--32672", "origin": {"flightPlaceId": "DEL", "displayCode": "DEL", "parent": {"flightPlaceId": "IDEL", "displayCode": "DEL", "name": "New Delhi", "type": "City"}, "name": "Indira Gandhi International ", "type": "Airport", "country": "India"}, "destination": {"flightPlaceId": "JFK", "displayCode": "JFK", "parent": {"flightPlaceId": "NYCA", "displayCode": "NYC", "name": "New York", "type": "City"}, "name": "New York John F. Kennedy", "type": "Airport", "country": "United States"}, "departure": "2025-03-07T02:30:00", "arrival": "2025-03-07T06:55:00", "durationInMinutes": 895, "flightNumber": "101", "marketingCarrier": {"id": -32672, "name": "Air India", "alternateId": "AI", "allianceId": 0, "displayCode": ""}, "operatingCarrier": {"id": -32672, "name": "Air India", "alternateId": "AI", "allianceId": 0, "displayCode": ""}}]}], "isSelfTransfer": false, "isProtectedSelfTransfer": false, "farePolicy": {"isChangeAllowed": false, "isPartiallyChangeable": false, "isCancellationAllowed": false, "isPartiallyRefundable": false}, "fareAttributes": {}, "tags": ["shortest"], "isMashUp": false, "hasFlexibleOptions": false, "score": 0.861455}, {"id": "10002-2503062020--32348-2-12712-2503071855", "price": {"raw": 54395.0, "formatted": "\u20b9\u00a054,395", "pricingOptionId": "H6i7mJHDFX-X"}, "legs": [{"id": "10002-2503062020--32348-2-12712-2503071855", "origin": {"id": "BLR", "entityId": "95673351", "name": "Bengaluru", "displayCode": "BLR", "city": "Bengaluru", "country": "India", "isHighlighted": false}, "destination": {"id": "JFK", "entityId": "95565058", "name": "New York John F. Kennedy", "displayCode": "JFK", "city": "New York", "country": "United States", "isHighlighted": false}, "durationInMinutes": 1985, "stopCount": 2, "isSmallestStops": false, "departure": "2025-03-06T20:20:00", "arrival": "2025-03-07T18:55:00", "timeDeltaInDays": 1, "carriers": {"marketing": [{"id": -32348, "alternateId": "EK", "logoUrl": "https://logos.skyscnr.com/images/airlines/favicon/EK.png", "name": "Emirates"}], "operationType": "fully_operated"}, "segments": [{"id": "10002-11182-2503062020-2503062300--32348", "origin": {"flightPlaceId": "BLR", "displayCode": "BLR", "parent": {"flightPlaceId": "IBLR", "displayCode": "BLR", "name": "Bengaluru", "type": "City"}, "name": "Bengaluru", "type": "Airport", "country": "India"}, "destination": {"flightPlaceId": "DXB", "displayCode": "DXB", "parent": {"flightPlaceId": "DXBA", "displayCode": "DXB", "name": "Dubai", "type": "City"}, "name": "Dubai", "type": "Airport", "country": "United Arab Emirates"}, "departure": "2025-03-06T20:20:00", "arrival": "2025-03-06T23:00:00", "durationInMinutes": 250, "flightNumber": "567", "marketingCarrier": {"id": -32348, "name": "Emirates", "alternateId": "EK", "allianceId": 0, "displayCode": ""}, "operatingCarrier": {"id": -32348, "name": "Emirates", "alternateId": "EK", "allianceId": 0, "displayCode": ""}}, {"id": "11182-14476-2503070905-2503071310--32348", "origin": {"flightPlaceId": "DXB", "displayCode": "DXB", "parent": {"flightPlaceId": "DXBA", "displayCode": "DXB", "name": "Dubai", "type": "City"}, "name": "Dubai", "type": "Airport", "country": "United Arab Emirates"}, "destination": {"flightPlaceId": "MXP", "displayCode": "MXP", "parent": {"flightPlaceId": "MILA", "displayCode": "MIL", "name": "Milan", "type": "City"}, "name": "Milan Malpensa", "type": "Airport", "country": "Italy"}, "departure": "2025-03-07T09:05:00", "arrival": "2025-03-07T13:10:00", "durationInMinutes": 425, "flightNumber": "205", "marketingCarrier": {"id": -32348, "name": "Emirates", "alternateId": "EK", "allianceId": 0, "displayCode": ""}, "operatingCarrier": {"id": -32348, "name": "Emirates", "alternateId": "EK", "allianceId": 0, "displayCode": ""}}, {"id": "14476-12712-2503071540-2503071855--32348", "origin": {"flightPlaceId": "MXP", "displayCode": "MXP", "parent": {"flightPlaceId": "MILA", "displayCode": "MIL", "name": "Milan", "type": "City"}, "name": "Milan Malpensa", "type": "Airport", "country": "Italy"}, "destination": {"flightPlaceId": "JFK", "displayCode": "JFK", "parent": {"flightPlaceId": "NYCA", "displayCode": "NYC", "name": "New York", "type": "City"}, "name": "New York John F. Kennedy", "type": "Airport", "country": "United States"}, "departure": "2025-03-07T15:40:00", "arrival": "2025-03-07T18:55:00", "durationInMinutes": 555, "flightNumber": "205", "marketingCarrier": {"id": -32348, "name": "Emirates", "alternateId": "EK", "allianceId": 0, "displayCode": ""}, "operatingCarrier": {"id": -32348, "name": "Emirates", "alternateId": "EK", "allianceId": 0, "displayCode": ""}}]}], "isSelfTransfer": false, "isProtectedSelfTransfer": false, "farePolicy": {"isChangeAllowed": false, "isPartiallyChangeable": false, "isCancellationAllowed": false, "isPartiallyRefundable": false}, "fareAttributes": {}, "tags": ["cheapest"], "isMashUp": false, "hasFlexibleOptions": false, "score": 0.781393}, {"id": "10002-2503062125--32672-1-12712-2503070655", "price": {"raw": 72562.53, "formatted": "\u20b9\u00a072,563", "pricingOptionId": "G013G5ejt3fw"}, "legs": [{"id": "10002-2503062125--32672-1-12712-2503070655", "origin": {"id": "BLR", "entityId": "95673351", "name": "Bengaluru", "displayCode": "BLR", "city": "Bengaluru", "country": "India", "isHighlighted": false}, "destination": {"id": "JFK", "entityId": "95565058", "name": "New York John F. Kennedy", "displayCode": "JFK", "city": "New York", "country": "United States", "isHighlighted": false}, "durationInMinutes": 1200, "stopCount": 1, "isSmallestStops": false, "departure": "2025-03-06T21:25:00", "arrival": "2025-03-07T06:55:00", "timeDeltaInDays": 1, "carriers": {"marketing": [{"id": -32672, "alternateId": "AI", "logoUrl": "https://logos.skyscnr.com/images/airlines/favicon/AI.png", "name": "Air India"}], "operationType": "fully_operated"}, "segments": [{"id": "10002-10075-2503062125-2503062335--32672", "origin": {"flightPlaceId": "BLR", "displayCode": "BLR", "parent": {"flightPlaceId": "IBLR", "displayCode": "BLR", "name": "Bengaluru", "type": "City"}, "name": "Bengaluru", "type": "Airport", "country": "India"}, "destination": {"flightPlaceId": "BOM", "displayCode": "BOM", "parent": {"flightPlaceId": "IBOM", "displayCode": "BOM", "name": "Mumbai", "type": "City"}, "name": "Mumbai", "type": "Airport", "country": "India"}, "departure": "2025-03-06T21:25:00", "arrival": "2025-03-06T23:35:00", "durationInMinutes": 130, "flightNumber": "2645", "marketingCarrier": {"id": -32672, "name": "Air India", "alternateId": "AI", "allianceId": 0, "displayCode": ""}, "operatingCarrier": {"id": -32672, "name": "Air India", "alternateId": "AI", "allianceId": 0, "displayCode": ""}}, {"id": "10075-12712-2503070145-2503070655--32672", "origin": {"flightPlaceId": "BOM", "displayCode": "BOM", "parent": {"flightPlaceId": "IBOM", "displayCode": "BOM", "name": "Mumbai", "type": "City"}, "name": "Mumbai", "type": "Airport", "country": "India"}, "destination": {"flightPlaceId": "JFK", "displayCode": "JFK", "parent": {"flightPlaceId": "NYCA", "displayCode": "NYC", "name": "New York", "type": "City"}, "name": "New York John F. Kennedy", "type": "Airport", "country": "United States"}, "departure": "2025-03-07T01:45:00", "arrival": "2025-03-07T06:55:00", "durationInMinutes": 940, "flightNumber": "119", "marketingCarrier": {"id": -32672, "name": "Air India", "alternateId": "AI", "allianceId": 0, "displayCode": ""}, "operatingCarrier": {"id": -32672, "name": "Air India", "alternateId": "AI", "allianceId": 0, "displayCode": ""}}]}], "isSelfTransfer": false, "isProtectedSelfTransfer": false, "farePolicy": {"isChangeAllowed": false, "isPartiallyChangeable": false, "isCancellationAllowed": false, "isPartiallyRefundable": false}, "fareAttributes": {}, "tags": ["second_cheapest", "second_shortest"], "isMashUp": false, "hasFlexibleOptions": false, "score": 0.654096}, {"id": "10002-2503062130--32339-1-12712-2503070840", "price": {"raw": 79039.51, "formatted": "\u20b9\u00a079,040", "pricingOptionId": "LAg21eOwl1jl"}, "legs": [{"id": "10002-2503062130--32339-1-12712-2503070840", "origin": {"id": "BLR", "entityId": "95673351", "name": "Bengaluru", "displayCode": "BLR", "city": "Bengaluru", "country": "India", "isHighlighted": false}, "destination": {"id": "JFK", "entityId": "95565058", "name": "New York John F. Kennedy", "displayCode": "JFK", "city": "New York", "country": "United States", "isHighlighted": false}, "durationInMinutes": 1300, "stopCount": 1, "isSmallestStops": false, "departure": "2025-03-06T21:30:00", "arrival": "2025-03-07T08:40:00", "timeDeltaInDays": 1, "carriers": {"marketing": [{"id": -32339, "alternateId": "60", "logoUrl": "https://logos.skyscnr.com/images/airlines/favicon/60.png", "name": "Etihad Airways"}], "operationType": "fully_operated"}, "segments": [{"id": "10002-9618-2503062130-2503070020--32339", "origin": {"flightPlaceId": "BLR", "displayCode": "BLR", "parent": {"flightPlaceId": "IBLR", "displayCode": "BLR", "name": "Bengaluru", "type": "City"}, "name": "Bengaluru", "type": "Airport", "country": "India"}, "destination": {"flightPlaceId": "AUH", "displayCode": "AUH", "parent": {"flightPlaceId": "AUHA", "displayCode": "AUH", "name": "Abu Dhabi", "type": "City"}, "name": "Zayed International", "type": "Airport", "country": "United Arab Emirates"}, "departure": "2025-03-06T21:30:00", "arrival": "2025-03-07T00:20:00", "durationInMinutes": 260, "flightNumber": "239", "marketingCarrier": {"id": -32339, "name": "Etihad Airways", "alternateId": "60", "allianceId": 0, "displayCode": ""}, "operatingCarrier": {"id": -32339, "name": "Etihad Airways", "alternateId": "60", "allianceId": 0, "displayCode": ""}}, {"id": "9618-12712-2503070250-2503070840--32339", "origin": {"flightPlaceId": "AUH", "displayCode": "AUH", "parent": {"flightPlaceId": "AUHA", "displayCode": "AUH", "name": "Abu Dhabi", "type": "City"}, "name": "Zayed International", "type": "Airport", "country": "United Arab Emirates"}, "destination": {"flightPlaceId": "JFK", "displayCode": "JFK", "parent": {"flightPlaceId": "NYCA", "displayCode": "NYC", "name": "New York", "type": "City"}, "name": "New York John F. Kennedy", "type": "Airport", "country": "United States"}, "departure": "2025-03-07T02:50:00", "arrival": "2025-03-07T08:40:00", "durationInMinutes": 890, "flightNumber": "1", "marketingCarrier": {"id": -32339, "name": "Etihad Airways", "alternateId": "60", "allianceId": 0, "displayCode": ""}, "operatingCarrier": {"id": -32339, "name": "Etihad Airways", "alternateId": "60", "allianceId": 0, "displayCode": ""}}]}], "isSelfTransfer": false, "isProtectedSelfTransfer": false, "farePolicy": {"isChangeAllowed": false, "isPartiallyChangeable": false, "isCancellationAllowed": false, "isPartiallyRefundable": false}, "fareAttributes": {}, "isMashUp": false, "hasFlexibleOptions": false, "score": 0.613312}, {"id": "10002-2503062025--32672-1-12712-2503070655", "price": {"raw": 72562.53, "formatted": "\u20b9\u00a072,563", "pricingOptionId": "tM9Ax2SkpfI6"}, "legs": [{"id": "10002-2503062025--32672-1-12712-2503070655", "origin": {"id": "BLR", "entityId": "95673351", "name": "Bengaluru", "displayCode": "BLR", "city": "Bengaluru", "country": "India", "isHighlighted": false}, "destination": {"id": "JFK", "entityId": "95565058", "name": "New York John F. Kennedy", "displayCode": "JFK", "city": "New York", "country": "United States", "isHighlighted": false}, "durationInMinutes": 1260, "stopCount": 1, "isSmallestStops": false, "departure": "2025-03-06T20:25:00", "arrival": "2025-03-07T06:55:00", "timeDeltaInDays": 1, "carriers": {"marketing": [{"id": -32672, "alternateId": "AI", "logoUrl": "https://logos.skyscnr.com/images/airlines/favicon/AI.png", "name": "Air India"}], "operationType": "fully_operated"}, "segments": [{"id": "10002-10075-2503062025-2503062235--32672", "origin": {"flightPlaceId": "BLR", "displayCode": "BLR", "parent": {"flightPlaceId": "IBLR", "displayCode": "BLR", "name": "Bengaluru", "type": "City"}, "name": "Bengaluru", "type": "Airport", "country": "India"}, "destination": {"flightPlaceId": "BOM", "displayCode": "BOM", "parent": {"flightPlaceId": "IBOM", "displayCode": "BOM", "name": "Mumbai", "type": "City"}, "name": "Mumbai", "type": "Airport", "country": "India"}, "departure": "2025-03-06T20:25:00", "arrival": "2025-03-06T22:35:00", "durationInMinutes": 130, "flightNumber": "2850", "marketingCarrier": {"id": -32672, "name": "Air India", "alternateId": "AI", "allianceId": 0, "displayCode": ""}, "operatingCarrier": {"id": -32672, "name": "Air India", "alternateId": "AI", "allianceId": 0, "displayCode": ""}}, {"id": "10075-12712-2503070145-2503070655--32672", "origin": {"flightPlaceId": "BOM", "displayCode": "BOM", "parent": {"flightPlaceId": "IBOM", "displayCode": "BOM", "name": "Mumbai", "type": "City"}, "name": "Mumbai", "type": "Airport", "country": "India"}, "destination": {"flightPlaceId": "JFK", "displayCode": "JFK", "parent": {"flightPlaceId": "NYCA", "displayCode": "NYC", "name": "New York", "type": "City"}, "name": "New York John F. Kennedy", "type": "Airport", "country": "United States"}, "departure": "2025-03-07T01:45:00", "arrival": "2025-03-07T06:55:00", "durationInMinutes": 940, "flightNumber": "119", "marketingCarrier": {"id": -32672, "name": "Air India", "alternateId": "AI", "allianceId": 0, "displayCode": ""}, "operatingCarrier": {"id": -32672, "name": "Air India", "alternateId": "AI", "allianceId": 0, "displayCode": ""}}]}], "isSelfTransfer": false, "isProtectedSelfTransfer": false, "farePolicy": {"isChangeAllowed": false, "isPartiallyChangeable": false, "isCancellationAllowed": false, "isPartiallyRefundable": false}, "fareAttributes": {}, "tags": ["third_cheapest"], "isMashUp": false, "hasFlexibleOptions": false, "score": 0.603525}, {"id": "10002-2503062030--32672-1-12712-2503070655", "price": {"raw": 74126.81, "formatted": "\u20b9\u00a074,127", "pricingOptionId": "BkiPz9XnXpor"}, "legs": [{"id": "10002-2503062030--32672-1-12712-2503070655", "origin": {"id": "BLR", "entityId": "95673351", "name": "Bengaluru", "displayCode": "BLR", "city": "Bengaluru", "country": "India", "isHighlighted": false}, "destination": {"id": "JFK", "entityId": "95565058", "name": "New York John F. Kennedy", "displayCode": "JFK", "city": "New York", "country": "United States", "isHighlighted": false}, "durationInMinutes": 1255, "stopCount": 1, "isSmallestStops": false, "departure": "2025-03-06T20:30:00", "arrival": "2025-03-07T06:55:00", "timeDeltaInDays": 1, "carriers": {"marketing": [{"id": -32672, "alternateId": "AI", "logoUrl": "https://logos.skyscnr.com/images/airlines/favicon/AI.png", "name": "Air India"}], "operationType": "fully_operated"}, "segments": [{"id": "10002-10957-2503062030-2503062330--32672", "origin": {"flightPlaceId": "BLR", "displayCode": "BLR", "parent": {"flightPlaceId": "IBLR", "displayCode": "BLR", "name": "Bengaluru", "type": "City"}, "name": "Bengaluru", "type": "Airport", "country": "India"}, "destination": {"flightPlaceId": "DEL", "displayCode": "DEL", "parent": {"flightPlaceId": "IDEL", "displayCode": "DEL", "name": "New Delhi", "type": "City"}, "name": "Indira Gandhi International ", "type": "Airport", "country": "India"}, "departure": "2025-03-06T20:30:00", "arrival": "2025-03-06T23:30:00", "durationInMinutes": 180, "flightNumber": "2661", "marketingCarrier": {"id": -32672, "name": "Air India", "alternateId": "AI", "allianceId": 0, "displayCode": ""}, "operatingCarrier": {"id": -32672, "name": "Air India", "alternateId": "AI", "allianceId": 0, "displayCode": ""}}, {"id": "10957-12712-2503070230-2503070655--32672", "origin": {"flightPlaceId": "DEL", "displayCode": "DEL", "parent": {"flightPlaceId": "IDEL", "displayCode": "DEL", "name": "New Delhi", "type": "City"}, "name": "Indira Gandhi International ", "type": "Airport", "country": "India"}, "destination": {"flightPlaceId": "JFK", "displayCode": "JFK", "parent": {"flightPlaceId": "NYCA", "displayCode": "NYC", "name": "New York", "type": "City"}, "name": "New York John F. Kennedy", "type": "Airport", "country": "United States"}, "departure": "2025-03-07T02:30:00", "arrival": "2025-03-07T06:55:00", "durationInMinutes": 895, "flightNumber": "101", "marketingCarrier": {"id": -32672, "name": "Air India", "alternateId": "AI", "allianceId": 0, "displayCode": ""}, "operatingCarrier": {"id": -32672, "name": "Air India", "alternateId": "AI", "allianceId": 0, "displayCode": ""}}]}], "isSelfTransfer": false, "isProtectedSelfTransfer": false, "farePolicy": {"isChangeAllowed": false, "isPartiallyChangeable": false, "isCancellationAllowed": false, "isPartiallyRefundable": false}, "fareAttributes": {}, "tags": ["third_shortest"], "isMashUp": false, "hasFlexibleOptions": false, "score": 0.595665}, {"id": "10002-2503061955--32672-1-12712-2503070655", "price": {"raw": 72562.53, "formatted": "\u20b9\u00a072,563", "pricingOptionId": "64LQKKqAnz3c"}, "legs": [{"id": "10002-2503061955--32672-1-12712-2503070655", "origin": {"id": "BLR", "entityId": "95673351", "name": "Bengaluru", "displayCode": "BLR", "city": "Bengaluru", "country": "India", "isHighlighted": false}, "destination": {"id": "JFK", "entityId": "95565058", "name": "New York John F. Kennedy", "displayCode": "JFK", "city": "New York", "country": "United States", "isHighlighted": false}, "durationInMinutes": 1290, "stopCount": 1, "isSmallestStops": false, "departure": "2025-03-06T19:55:00", "arrival": "2025-03-07T06:55:00", "timeDeltaInDays": 1, "carriers": {"marketing": [{"id": -32672, "alternateId": "AI", "logoUrl": "https://logos.skyscnr.com/images/airlines/favicon/AI.png", "name": "Air India"}], "operationType": "fully_operated"}, "segments": [{"id": "10002-10075-2503061955-2503062150--32672", "origin": {"flightPlaceId": "BLR", "displayCode": "BLR", "parent": {"flightPlaceId": "IBLR", "displayCode": "BLR", "name": "Bengaluru", "type": "City"}, "name": "Bengaluru", "type": "Airport", "country": "India"}, "destination": {"flightPlaceId": "BOM", "displayCode": "BOM", "parent": {"flightPlaceId": "IBOM", "displayCode": "BOM", "name": "Mumbai", "type": "City"}, "name": "Mumbai", "type": "Airport", "country": "India"}, "departure": "2025-03-06T19:55:00", "arrival": "2025-03-06T21:50:00", "durationInMinutes": 115, "flightNumber": "2864", "marketingCarrier": {"id": -32672, "name": "Air India", "alternateId": "AI", "allianceId": 0, "displayCode": ""}, "operatingCarrier": {"id": -32672, "name": "Air India", "alternateId": "AI", "allianceId": 0, "displayCode": ""}}, {"id": "10075-12712-2503070145-2503070655--32672", "origin": {"flightPlaceId": "BOM", "displayCode": "BOM", "parent": {"flightPlaceId": "IBOM", "displayCode": "BOM", "name": "Mumbai", "type": "City"}, "name": "Mumbai", "type": "Airport", "country": "India"}, "destination": {"flightPlaceId": "JFK", "displayCode": "JFK", "parent": {"flightPlaceId": "NYCA", "displayCode": "NYC", "name": "New York", "type": "City"}, "name": "New York John F. Kennedy", "type": "Airport", "country": "United States"}, "departure": "2025-03-07T01:45:00", "arrival": "2025-03-07T06:55:00", "durationInMinutes": 940, "flightNumber": "119", "marketingCarrier": {"id": -32672, "name": "Air India", "alternateId": "AI", "allianceId": 0, "displayCode": ""}, "operatingCarrier": {"id": -32672, "name": "Air India", "alternateId": "AI", "allianceId": 0, "displayCode": ""}}]}], "isSelfTransfer": false, "isProtectedSelfTransfer": false, "farePolicy": {"isChangeAllowed": false, "isPartiallyChangeable": false, "isCancellationAllowed": false, "isPartiallyRefundable": false}, "fareAttributes": {}, "isMashUp": false, "hasFlexibleOptions": false, "score": 0.58724}, {"id": "10002-2503061920--32672-1-12712-2503070655", "price": {"raw": 72562.53, "formatted": "\u20b9\u00a072,563", "pricingOptionId": "pIzYp8XdAO-M"}, "legs": [{"id": "10002-2503061920--32672-1-12712-2503070655", "origin": {"id": "BLR", "entityId": "95673351", "name": "Bengaluru", "displayCode": "BLR", "city": "Bengaluru", "country": "India", "isHighlighted": false}, "destination": {"id": "JFK", "entityId": "95565058", "name": "New York John F. Kennedy", "displayCode": "JFK", "city": "New York", "country": "United States", "isHighlighted": false}, "durationInMinutes": 1325, "stopCount": 1, "isSmallestStops": false, "departure": "2025-03-06T19:20:00", "arrival": "2025-03-07T06:55:00", "timeDeltaInDays": 1, "carriers": {"marketing": [{"id": -32672, "alternateId": "AI", "logoUrl": "https://logos.skyscnr.com/images/airlines/favicon/AI.png", "name": "Air India"}], "operationType": "fully_operated"}, "segments": [{"id": "10002-10075-2503061920-2503062130--32672", "origin": {"flightPlaceId": "BLR", "displayCode": "BLR", "parent": {"flightPlaceId": "IBLR", "displayCode": "BLR", "name": "Bengaluru", "type": "City"}, "name": "Bengaluru", "type": "Airport", "country": "India"}, "destination": {"flightPlaceId": "BOM", "displayCode": "BOM", "parent": {"flightPlaceId": "IBOM", "displayCode": "BOM", "name": "Mumbai", "type": "City"}, "name": "Mumbai", "type": "Airport", "country": "India"}, "departure": "2025-03-06T19:20:00", "arrival": "2025-03-06T21:30:00", "durationInMinutes": 130, "flightNumber": "2610", "marketingCarrier": {"id": -32672, "name": "Air India", "alternateId": "AI", "allianceId": 0, "displayCode": ""}, "operatingCarrier": {"id": -32672, "name": "Air India", "alternateId": "AI", "allianceId": 0, "displayCode": ""}}, {"id": "10075-12712-2503070145-2503070655--32672", "origin": {"flightPlaceId": "BOM", "displayCode": "BOM", "parent": {"flightPlaceId": "IBOM", "displayCode": "BOM", "name": "Mumbai", "type": "City"}, "name": "Mumbai", "type": "Airport", "country": "India"}, "destination": {"flightPlaceId": "JFK", "displayCode": "JFK", "parent": {"flightPlaceId": "NYCA", "displayCode": "NYC", "name": "New York", "type": "City"}, "name": "New York John F. Kennedy", "type": "Airport", "country": "United States"}, "departure": "2025-03-07T01:45:00", "arrival": "2025-03-07T06:55:00", "durationInMinutes": 940, "flightNumber": "119", "marketingCarrier": {"id": -32672, "name": "Air India", "alternateId": "AI", "allianceId": 0, "displayCode": ""}, "operatingCarrier": {"id": -32672, "name": "Air India", "alternateId": "AI", "allianceId": 0, "displayCode": ""}}]}], "isSelfTransfer": false, "isProtectedSelfTransfer": false, "farePolicy": {"isChangeAllowed": false, "isPartiallyChangeable": false, "isCancellationAllowed": false, "isPartiallyRefundable": false}, "fareAttributes": {}, "isMashUp": false, "hasFlexibleOptions": false, "score": 0.566801}, {"id": "10002-2503061845--32672-1-12712-2503070655", "price": {"raw": 74128.55, "formatted": "\u20b9\u00a074,129", "pricingOptionId": "dGv5jL9q7gZu"}, "legs": [{"id": "10002-2503061845--32672-1-12712-2503070655", "origin": {"id": "BLR", "entityId": "95673351", "name": "Bengaluru", "displayCode": "BLR", "city": "Bengaluru", "country": "India", "isHighlighted": false}, "destination": {"id": "JFK", "entityId": "95565058", "name": "New York John F. Kennedy", "displayCode": "JFK", "city": "New York", "country": "United States", "isHighlighted": false}, "durationInMinutes": 1360, "stopCount": 1, "isSmallestStops": false, "departure": "2025-03-06T18:45:00", "arrival": "2025-03-07T06:55:00", "timeDeltaInDays": 1, "carriers": {"marketing": [{"id": -32672, "alternateId": "AI", "logoUrl": "https://logos.skyscnr.com/images/airlines/favicon/AI.png", "name": "Air India"}], "operationType": "fully_operated"}, "segments": [{"id": "10002-10957-2503061845-2503062140--32672", "origin": {"flightPlaceId": "BLR", "displayCode": "BLR", "parent": {"flightPlaceId": "IBLR", "displayCode": "BLR", "name": "Bengaluru", "type": "City"}, "name": "Bengaluru", "type": "Airport", "country": "India"}, "destination": {"flightPlaceId": "DEL", "displayCode": "DEL", "parent": {"flightPlaceId": "IDEL", "displayCode": "DEL", "name": "New Delhi", "type": "City"}, "name": "Indira Gandhi International ", "type": "Airport", "country": "India"}, "departure": "2025-03-06T18:45:00", "arrival": "2025-03-06T21:40:00", "durationInMinutes": 175, "flightNumber": "2802", "marketingCarrier": {"id": -32672, "name": "Air India", "alternateId": "AI", "allianceId": 0, "displayCode": ""}, "operatingCarrier": {"id": -32672, "name": "Air India", "alternateId": "AI", "allianceId": 0, "displayCode": ""}}, {"id": "10957-12712-2503070230-2503070655--32672", "origin": {"flightPlaceId": "DEL", "displayCode": "DEL", "parent": {"flightPlaceId": "IDEL", "displayCode": "DEL", "name": "New Delhi", "type": "City"}, "name": "Indira Gandhi International ", "type": "Airport", "country": "India"}, "destination": {"flightPlaceId": "JFK", "displayCode": "JFK", "parent": {"flightPlaceId": "NYCA", "displayCode": "NYC", "name": "New York", "type": "City"}, "name": "New York John F. Kennedy", "type": "Airport", "country": "United States"}, "departure": "2025-03-07T02:30:00", "arrival": "2025-03-07T06:55:00", "durationInMinutes": 895, "flightNumber": "101", "marketingCarrier": {"id": -32672, "name": "Air India", "alternateId": "AI", "allianceId": 0, "displayCode": ""}, "operatingCarrier": {"id": -32672, "name": "Air India", "alternateId": "AI", "allianceId": 0, "displayCode": ""}}]}], "isSelfTransfer": false, "isProtectedSelfTransfer": false, "farePolicy": {"isChangeAllowed": false, "isPartiallyChangeable": false, "isCancellationAllowed": false, "isPartiallyRefundable": false}, "fareAttributes": {}, "isMashUp": false, "hasFlexibleOptions": false, "score": 0.552678}], "messages": [], "filterStats": {"duration": {"min": 1165, "max": 1985, "multiCityMin": 1165, "multiCityMax": 1985}, "airports": [{"city": "Bengaluru", "airports": [{"id": "BLR", "entityId": "95673351", "name": "Bengaluru"}]}, {"city": "New York", "airports": [{"id": "JFK", "entityId": "95565058", "name": "New York John F. Kennedy"}]}], "carriers": [{"id": -32672, "alternateId": "AI", "logoUrl": "https://logos.skyscnr.com/images/airlines/favicon/AI.png", "name": "Air India"}, {"id": -32348, "alternateId": "EK", "logoUrl": "https://logos.skyscnr.com/images/airlines/favicon/EK.png", "name": "Emirates"}, {"id": -32339, "alternateId": "60", "logoUrl": "https://logos.skyscnr.com/images/airlines/favicon/60.png", "name": "Etihad Airways"}], "stopPrices": {"direct": {"isPresent": false}, "one": {"isPresent": true, "formattedPrice": "\u20b9\u00a072,563"}, "twoOrMore": {"isPresent": true, "formattedPrice": "\u20b9\u00a054,395"}}}, "flightsSessionId": "415ee37e-f6d3-4b88-b235-6ee4d2e1ee99", "destinationImageUrl": "https://content.skyscnr.com/m/3719e8f4a5daf43d/original/Flights-Placeholder.jpg", "token": "eyJhIjoxLCJjIjowLCJpIjowLCJjYyI6ImVjb25vbXkiLCJvIjoiQkxSIiwiZCI6IkpGSyIsImQxIjoiMjAyNS0wMy0wNiJ9"}, "status": true, "message": "Successful"}